serverless_crud/__init__.py
serverless_crud/actions/__init__.py
serverless_crud/actions/base.py
serverless_crud/actions/create.py
serverless_crud/actions/delete.py
serverless_crud/actions/get.py
serverless_crud/actions/search.py
serverless_crud/actions/update.py
serverless_crud/api.py
serverless_crud/appsync/__init__.py
serverless_crud/appsync/api.py
serverless_crud/appsync/utils.py
serverless_crud/aws/__init__.py
serverless_crud/aws/iam.py
serverless_crud/builders/__init__.py
serverless_crud/builders/graphql.py
serverless_crud/dynamodb/__init__.py
serverless_crud/dynamodb/annotation.py
serverless_crud/dynamodb/builder.py
serverless_crud/dynamodb/utils.py
serverless_crud/exceptions.py
serverless_crud/graphql/__init__.py
serverless_crud/graphql/api.py
serverless_crud/logger.py
serverless_crud/model.py
serverless_crud/rest/__init__.py
serverless_crud/rest/api.py
serverless_crud/rest/http.py
serverless_crud/rest/utils.py
serverless_crud/service.py
serverless_crud/utils.py
python_serverless_crud-1.4.1.dist-info/LICENSE
python_serverless_crud-1.4.1.dist-info/METADATA
python_serverless_crud-1.4.1.dist-info/WHEEL
python_serverless_crud-1.4.1.dist-info/RECORD
