Metadata-Version: 2.1
Name: python-serverless-crud
Version: 1.4.1
Summary: Simple and powerful tool for quick serverless data management via API. 
Home-page: https://github.com/epsylabs/python-serverless-crud
License: MIT
Keywords: library,serverless
Author: Epsy
Author-email: engineering@epsyhealth.com
Requires-Python: >=3.8,<4.0
Classifier: Intended Audience :: Developers
Classifier: License :: OSI Approved :: MIT License
Classifier: Programming Language :: Python
Classifier: Programming Language :: Python :: 3
Classifier: Programming Language :: Python :: 3.8
Classifier: Programming Language :: Python :: 3.9
Classifier: Programming Language :: Python :: 3.10
Classifier: Programming Language :: Python :: 3.11
Classifier: Programming Language :: Python :: 3 :: Only
Provides-Extra: sentry
Requires-Dist: PyJWT (>=2.4,<3.0)
Requires-Dist: aws-lambda-powertools[pydantic] (>=1.24,<2.0)
Requires-Dist: graphene (>=3.0,<4.0)
Requires-Dist: graphene-pydantic (>=0.3.0,<0.4.0)
Requires-Dist: inflect (>=5.3.0,<6.0.0)
Requires-Dist: sentry-sdk (>=1.5,<2.0) ; extra == "sentry"
Requires-Dist: stringcase (>=1.2.0,<2.0.0)
Project-URL: Repository, https://github.com/epsylabs/python-serverless-crud
